README
setup.py
django_googlecharts.egg-info/PKG-INFO
django_googlecharts.egg-info/SOURCES.txt
django_googlecharts.egg-info/dependency_links.txt
django_googlecharts.egg-info/requires.txt
django_googlecharts.egg-info/top_level.txt
googlecharts/__init__.py
googlecharts/models.py
googlecharts/runtests.py
googlecharts/tests.py
googlecharts/templatetags/__init__.py
googlecharts/templatetags/charts.py