Metadata-Version: 1.0
Name: django-googlecharts
Version: 1.0-alpha-1
Summary: Django template tags to generate charts using the Google chart API.
Home-page: http://github.com/jacobian/django-googlecharts
Author: Jacob Kaplan-Moss
Author-email: jacob@jacobian.org
License: BSD
Keywords: django charts templates
Platform: UNKNOWN
Classifier: Development Status :: 3 - Alpha
Classifier: Environment :: Plugins
Classifier: Framework :: Django
Classifier: Intended Audience :: Developers
Classifier: License :: OSI Approved :: BSD License
Classifier: Programming Language :: Python
Classifier: Topic :: Software Development :: Libraries :: Python Modules
